configyaml/__init__.py
configyaml/cli.py
configyaml/configyaml.py
configyaml/errors.py
configyaml/loader.py
configyaml/validator.py
configyaml/config/__init__.py
configyaml/config/base.py
configyaml/config/choice.py
configyaml/config/dict.py
configyaml/config/list.py
configyaml/config/nodes.py
configyaml-0.5.1.dist-info/DESCRIPTION.rst
configyaml-0.5.1.dist-info/METADATA
configyaml-0.5.1.dist-info/RECORD
configyaml-0.5.1.dist-info/WHEEL
configyaml-0.5.1.dist-info/entry_points.txt
configyaml-0.5.1.dist-info/metadata.json
configyaml-0.5.1.dist-info/top_level.txt
