Metadata-Version: 2.0
Name: configyaml
Version: 0.5.1
Summary: A config loading and parsing package
Home-page: https://github.com/dropseedlabs/config-loader
Author: Dropseed
Author-email: python@dropseed.io
License: MIT license
Keywords: configyaml
Platform: UNKNOWN
Classifier: Development Status :: 2 - Pre-Alpha
Classifier: Intended Audience :: Developers
Classifier: License :: OSI Approved :: MIT License
Classifier: Natural Language :: English
Classifier: Programming Language :: Python :: 2
Classifier: Programming Language :: Python :: 2.7
Classifier: Programming Language :: Python :: 3
Classifier: Programming Language :: Python :: 3.3
Classifier: Programming Language :: Python :: 3.4
Classifier: Programming Language :: Python :: 3.5
Classifier: Programming Language :: Python :: 3.6
Requires-Dist: Click (>=6.0)
Requires-Dist: pyyaml
